ckeditor_filer/__init__.py
ckeditor_filer/admin.py
ckeditor_filer/apps.py
ckeditor_filer/models.py
ckeditor_filer/tests.py
ckeditor_filer/urls.py
ckeditor_filer/views.py
ckeditor_filer/locale/ru/LC_MESSAGES/django.mo
ckeditor_filer/locale/ru/LC_MESSAGES/django.po
ckeditor_filer/migrations/__init__.py
ckeditor_filer/static/ckeditor/ckeditor/plugins/filer/plugin.js
ckeditor_filer/static/ckeditor/ckeditor/plugins/filer/dialogs/filer.js
ckeditor_filer/static/ckeditor/ckeditor/plugins/filer/icons/filer.png
ckeditor_filer/static/ckeditor/ckeditor/plugins/filer/icons/hidpi/filer.png
ckeditor_filer/static/ckeditor/ckeditor/plugins/filer/lang/en.js
ckeditor_filer/static/ckeditor/ckeditor/plugins/filer/lang/ru.js
django_ckeditor_filer-1.2.0.dist-info/METADATA
django_ckeditor_filer-1.2.0.dist-info/WHEEL
django_ckeditor_filer-1.2.0.dist-info/top_level.txt
django_ckeditor_filer-1.2.0.dist-info/RECORD
