Metadata-Version: 2.1
Name: django-ckeditor-filer
Version: 1.2.0
Summary: Adds a button in the django-ckeditor to load images into the django-filer
Home-page: https://bitbucket.org/TheDeadOne/django-ckeditor-filer/
Author: Sergey Gornostaev
Author-email: sergey@gornostaev.dev
License: BSD license
Platform: UNKNOWN
Classifier: Development Status :: 5 - Production/Stable
Classifier: Environment :: Web Environment
Classifier: Framework :: Django
Classifier: Intended Audience :: Developers
Classifier: License :: OSI Approved :: BSD License
Classifier: Programming Language :: Python
Classifier: Programming Language :: Python :: 2.7
Classifier: Programming Language :: Python :: 3.5
Classifier: Programming Language :: Python :: 3.6
Classifier: Programming Language :: Python :: 3.7
Classifier: Topic :: Software Development :: Libraries :: Python Modules
Classifier: Natural Language :: Russian
Requires-Dist: django-filer
Requires-Dist: django-ckeditor
